{"cameraMode":{"drawMode":0,"name":"Shaded","section":"Shading Mode"},"sceneLighting":true,"audioPlay":false,"sceneViewState":{"m_AlwaysRefresh":false,"showFog":true,"showSkybox":true,"showFlares":true,"showImageEffects":true,"showParticleSystems":true,"showVisualEffectGraphs":true,"m_FxEnabled":true},"in2DMode":false,"pivot":{"x":28.7259521484375,"y":-3.6926279067993166,"z":74.42892456054688},"rotation":{"x":-0.06293746083974838,"y":-0.235487699508667,"z":0.015294074080884457,"w":-0.9697615504264832},"size":39.9581298828125,"orthographic":false}